{"Ads": 
  [
    {
      "select_main_ads": "FACEBOOK",
      "select_backup_ads":"APPLOVIN-D",
      "main_ads_banner": "1826553814453838_1826554364453783",
      "main_ads_intertitial":"1826553814453838_1826554407787112",
      "backup_ads_banner":"ca-app-pub-9525858816840213/6684624628",
      "backup_ads_intertitial":"ca-app-pub-9525858816840213/6287386419",
      "open_ads_admob":"ca-app-pub-9525858816840213/1194841838",
      "open_ads_alien":"",
      "open_ads_max":"1",
      "interval_intertitial": 1,
      "initialize_sdk":"107355779",
      "initialize_sdk_backup_ads":"",
      "high_paying_keyword_1": "",
      "high_paying_keyword_2": "",
      "high_paying_keyword_3": "",
      "high_paying_keyword_4": "",
      "high_paying_keyword_5": "",
      "status_app": "0",
      "link_redirect": "https://"

    }
  ],
     "Categories": [
    {
      "category": "Yearbook",
      "image_link": "https://raw.githubusercontent.com/darwindroid/gambar/main/yb4.png"

    }
  ],

  "Item": [
    {
      "id": 1,
      "category": "Yearbook",
      "title": "Yearbook1",
      "image_link": "https://raw.githubusercontent.com/darwindroid/gambar/main/yb1.png"
    },
    {
      "id": 2,
      "category": "Yearbook",
      "title": "Yearbook2",
      "image_link": "https://raw.githubusercontent.com/darwindroid/gambar/main/yb2.png"
    },
    {
      "id": 3,
      "category": "Yearbook",
      "title": "Yearbook3",
      "image_link": "https://raw.githubusercontent.com/darwindroid/gambar/main/yb3.png"
    },
    {
      "id": 4,
      "category": "Yearbook",
      "title": "Yearbook4",
      "image_link": "https://raw.githubusercontent.com/darwindroid/gambar/main/yb4.png"
    },
    {
      "id": 5,
      "category": "Yearbook",
      "title": "Yearbook5",
      "image_link": "https://raw.githubusercontent.com/darwindroid/gambar/main/yb5.png"
    },
    {
      "id": 6,
      "category": "Yearbook",
      "title": "Yearbook6",
      "image_link": "https://raw.githubusercontent.com/darwindroid/gambar/main/yb6.png"
    },
    {
      "id": 7,
      "category": "Yearbook",
      "title": "Yearbook7 ",
      "image_link": "https://raw.githubusercontent.com/darwindroid/gambar/main/yb7.png"
    },
    {
      "id": 8,
      "category": "Yearbook",
      "title": "Yearbook8",
      "image_link": "https://raw.githubusercontent.com/darwindroid/gambar/main/yb8.png"
    },
    {
      "id": 9,
      "category": "Yearbook",
      "title": "Yearbook9",
      "image_link": "https://raw.githubusercontent.com/darwindroid/gambar/main/yb9.png"
    },
    {
      "id": 10,
      "category": "Yearbook",
      "title": "Yearbook10",
      "image_link": "https://raw.githubusercontent.com/darwindroid/gambar/main/yb10.png"
    }


  ]
}
